COPYING.txt
LICENSE
README.md
setup.cfg
setup.py
JYTools/DB.py
JYTools/MyEmail.py
JYTools/MyRequests.py
JYTools/StringTool.py
JYTools/__init__.py
JYTools.egg-info/PKG-INFO
JYTools.egg-info/SOURCES.txt
JYTools.egg-info/dependency_links.txt
JYTools.egg-info/entry_points.txt
JYTools.egg-info/not-zip-safe
JYTools.egg-info/requires.txt
JYTools.egg-info/top_level.txt
JYTools/JYWorker/DAG.py
JYTools/JYWorker/UploadLog.py
JYTools/JYWorker/_Task.py
JYTools/JYWorker/_Worker.py
JYTools/JYWorker/__init__.py
JYTools/JYWorker/_async.py
JYTools/JYWorker/_config.py
JYTools/JYWorker/_du.py
JYTools/JYWorker/_exception.py
JYTools/JYWorker/_func_task.py
JYTools/JYWorker/_redis.py
JYTools/JYWorker/cli.py
JYTools/JYWorker/function.py
JYTools/JYWorker/help.py
JYTools/JYWorker/util.py
JYTools/JYWorker/console/__init__.py
JYTools/JYWorker/console/func_task.py
JYTools/demo/MultWorker.zh.py
JYTools/demo/ResultWorker.zh.py
JYTools/demo/__init__.py
JYTools/demo/my_worker.py
JYTools/demo/pbs_agent_worker.py
JYTools/demo/redis_stat.py
JYTools/demo/some_funcs.py
JYTools/demo/test.zh.py
JYTools/demo/test_fun_task_group.py
JYTools/demo/use_func_task.py
JYTools/demo/workerlog.py
JYTools/demo/asyncWorker/__init__.py
JYTools/demo/asyncWorker/aysncStatWorker.zh.py
JYTools/demo/asyncWorker/pipelineWorker.py
JYTools/demo/asyncWorker/plusWorker.zh.py
JYTools/demo/asyncWorker/test.zh.py
JYTools/util/__init__.py
JYTools/util/constants.py
JYTools/util/file.py
JYTools/util/loader.py
JYTools/util/string_rich.py
JYTools/util/strong.py