Metadata-Version: 2.1
Name: JYTools
Version: 2.1.3
Summary: Jing Yun Tools Library
Home-page: https://github.com/meisanggou/Tools
Author: meisanggou
Author-email: zhou5315938@163.com
License: MIT
License-File: LICENSE
License-File: COPYING.txt
